{
  "newSuppliers": [
    {
      "id": 14,
      "name": "Caravan Coffee Roasters",
      "contact": "Mark Thompson",
      "lead_time": "1-2 days",
      "mcp_id": "caravan_coffee",
      "email": "wholesale@caravancoffee.co.uk",
      "phone": "+44 20 7101 1190",
      "address": "1 Granary Square, London N1C 4AA",
      "kosher_certified": true,
      "delivery_schedule": "Mon, Wed, Fri",
      "minimum_order": 50
    },
    {
      "id": 15,
      "name": "Union Hand-Roasted Coffee",
      "contact": "Sarah Mills",
      "lead_time": "2-3 days",
      "mcp_id": "union_coffee",
      "email": "trade@unionroasted.com",
      "phone": "+44 20 7474 8990",
      "address": "Unit 2, East Dulwich, London SE22 8EF",
      "kosher_certified": true,
      "delivery_schedule": "Tue, Thu",
      "minimum_order": 40
    },
    {
      "id": 16,
      "name": "Monmouth Coffee Company",
      "contact": "James Wilson",
      "lead_time": "1-2 days",
      "mcp_id": "monmouth_coffee",
      "email": "wholesale@monmouthcoffee.co.uk",
      "phone": "+44 20 7232 3010",
      "address": "2 Park Street, London SE1 9AB",
      "kosher_certified": false,
      "delivery_schedule": "Daily",
      "minimum_order": 30
    },
    {
      "id": 17,
      "name": "Postcard Teas",
      "contact": "Timothy d'Offay",
      "lead_time": "2-3 days",
      "mcp_id": "postcard_teas",
      "email": "trade@postcardteas.com",
      "phone": "+44 20 7629 3654",
      "address": "9 Dering Street, London W1S 1AG",
      "kosher_certified": true,
      "delivery_schedule": "Mon, Thu",
      "minimum_order": 25
    },
    {
      "id": 18,
      "name": "Rare Tea Company",
      "contact": "Henrietta Lovell",
      "lead_time": "3-4 days",
      "mcp_id": "rare_tea",
      "email": "orders@rareteacompany.com",
      "phone": "+44 20 7681 0115",
      "address": "21 Wapping Wall, London E1W 3SG",
      "kosher_certified": true,
      "delivery_schedule": "Tue, Fri",
      "minimum_order": 30
    },
    {
      "id": 19,
      "name": "Galeta Wholesale Bakery",
      "contact": "Maria Gonzalez",
      "lead_time": "1 day",
      "mcp_id": "galeta_bakery",
      "email": "orders@galeta.co.uk",
      "phone": "+44 20 8964 0660",
      "address": "Unit 7, London NW10 6TP",
      "kosher_certified": true,
      "delivery_schedule": "Daily",
      "minimum_order": 60
    },
    {
      "id": 20,
      "name": "Exploding Bakery",
      "contact": "Alex Turner",
      "lead_time": "1-2 days",
      "mcp_id": "exploding_bakery",
      "email": "wholesale@explodingbakery.com",
      "phone": "+44 1392 427 900",
      "address": "Unit 4, Exeter EX5 2UL",
      "kosher_certified": false,
      "delivery_schedule": "Mon, Wed, Fri",
      "minimum_order": 50
    },
    {
      "id": 21,
      "name": "Bread Ahead Bakery",
      "contact": "Matthew Jones",
      "lead_time": "1 day",
      "mcp_id": "bread_ahead",
      "email": "wholesale@breadahead.com",
      "phone": "+44 20 7403 5444",
      "address": "Borough Market, London SE1 9AF",
      "kosher_certified": true,
      "delivery_schedule": "Daily",
      "minimum_order": 40
    },
    {
      "id": 22,
      "name": "Crosstown Doughnuts",
      "contact": "JP Then",
      "lead_time": "1-2 days",
      "mcp_id": "crosstown",
      "email": "wholesale@crosstowndoughnuts.com",
      "phone": "+44 20 3633 9676",
      "address": "Unit 10, London SW8 3NS",
      "kosher_certified": false,
      "delivery_schedule": "Tue, Thu, Sat",
      "minimum_order": 36
    },
    {
      "id": 23,
      "name": "Deliciously Ella Deli",
      "contact": "Ella Mills",
      "lead_time": "2-3 days",
      "mcp_id": "deliciously_ella",
      "email": "wholesale@deliciouslyella.com",
      "phone": "+44 20 7629 2112",
      "address": "18-20 Weighhouse St, London W1K 5LU",
      "kosher_certified": true,
      "delivery_schedule": "Mon, Wed, Fri",
      "minimum_order": 40
    },
    {
      "id": 24,
      "name": "Whole Foods Market Wholesale",
      "contact": "John Smith",
      "lead_time": "1-2 days",
      "mcp_id": "whole_foods",
      "email": "wholesale.uk@wholefoods.com",
      "phone": "+44 20 7368 4500",
      "address": "63-97 Kensington High St, London W8 5SE",
      "kosher_certified": true,
      "delivery_schedule": "Daily",
      "minimum_order": 100
    },
    {
      "id": 25,
      "name": "New Covent Garden Market Direct",
      "contact": "Market Team",
      "lead_time": "Same day",
      "mcp_id": "ncg_market",
      "email": "direct@newcoventgardenmarket.com",
      "phone": "+44 20 7720 2211",
      "address": "Nine Elms Lane, London SW8 5PA",
      "kosher_certified": true,
      "delivery_schedule": "Daily",
      "minimum_order": 50
    }
  ],
  "newProducts": [
    {
      "id": 60,
      "name": "House Blend Coffee Beans",
      "category": "specialty_coffee",
      "suppliers": [
        {"supplier_id": 14, "price": 18.50, "quality_score": 9.2},
        {"supplier_id": 15, "price": 17.00, "quality_score": 8.8},
        {"supplier_id": 9, "price": 19.00, "quality_score": 8.5}
      ],
      "unit": "kg",
      "reorder_point": 20,
      "optimal_stock": 40,
      "consumption_rate": 5,
      "daily_usage": 5,
      "order_quantity": 25,
      "lead_time": 2,
      "lead_time_unit": "daily",
      "kosher_certified": true,
      "storage_temp": "room_temp",
      "shelf_life_days": 30
    },
    {
      "id": 61,
      "name": "Single Origin Ethiopian Coffee",
      "category": "specialty_coffee",
      "suppliers": [
        {"supplier_id": 14, "price": 24.00, "quality_score": 9.5},
        {"supplier_id": 16, "price": 22.50, "quality_score": 9.3},
        {"supplier_id": 15, "price": 23.00, "quality_score": 9.0}
      ],
      "unit": "kg",
      "reorder_point": 10,
      "optimal_stock": 20,
      "consumption_rate": 3,
      "daily_usage": 3,
      "order_quantity": 15,
      "lead_time": 2,
      "lead_time_unit": "daily",
      "kosher_certified": true,
      "storage_temp": "room_temp",
      "shelf_life_days": 30
    },
    {
      "id": 62,
      "name": "Decaf Coffee Beans",
      "category": "specialty_coffee",
      "suppliers": [
        {"supplier_id": 15, "price": 19.00, "quality_score": 8.5},
        {"supplier_id": 14, "price": 20.00, "quality_score": 8.8},
        {"supplier_id": 9, "price": 18.50, "quality_score": 8.2}
      ],
      "unit": "kg",
      "reorder_point": 8,
      "optimal_stock": 15,
      "consumption_rate": 2,
      "daily_usage": 2,
      "order_quantity": 10,
      "lead_time": 2,
      "lead_time_unit": "daily",
      "kosher_certified": true,
      "storage_temp": "room_temp",
      "shelf_life_days": 30
    },
    {
      "id": 63,
      "name": "Earl Grey Premium Tea",
      "category": "artisan_teas",
      "suppliers": [
        {"supplier_id": 17, "price": 32.00, "quality_score": 9.4},
        {"supplier_id": 18, "price": 35.00, "quality_score": 9.6},
        {"supplier_id": 10, "price": 28.00, "quality_score": 8.5}
      ],
      "unit": "kg",
      "reorder_point": 3,
      "optimal_stock": 6,
      "consumption_rate": 1,
      "daily_usage": 1,
      "order_quantity": 5,
      "lead_time": 3,
      "lead_time_unit": "daily",
      "kosher_certified": true,
      "storage_temp": "room_temp",
      "shelf_life_days": 365
    },
    {
      "id": 64,
      "name": "Organic Matcha Powder",
      "category": "artisan_teas",
      "suppliers": [
        {"supplier_id": 18, "price": 45.00, "quality_score": 9.8},
        {"supplier_id": 17, "price": 42.00, "quality_score": 9.5},
        {"supplier_id": 24, "price": 40.00, "quality_score": 9.0}
      ],
      "unit": "kg",
      "reorder_point": 2,
      "optimal_stock": 4,
      "consumption_rate": 0.5,
      "daily_usage": 0.5,
      "order_quantity": 3,
      "lead_time": 4,
      "lead_time_unit": "daily",
      "kosher_certified": true,
      "storage_temp": "cool",
      "shelf_life_days": 180
    },
    {
      "id": 65,
      "name": "Gluten-Free Chocolate Brownies",
      "category": "gluten_free",
      "suppliers": [
        {"supplier_id": 20, "price": 2.50, "quality_score": 9.0},
        {"supplier_id": 23, "price": 2.80, "quality_score": 9.2},
        {"supplier_id": 19, "price": 2.40, "quality_score": 8.7}
      ],
      "unit": "units",
      "reorder_point": 40,
      "optimal_stock": 80,
      "consumption_rate": 20,
      "daily_usage": 20,
      "order_quantity": 60,
      "lead_time": 1,
      "lead_time_unit": "daily",
      "kosher_certified": true,
      "storage_temp": "room_temp",
      "shelf_life_days": 5
    },
    {
      "id": 66,
      "name": "Vegan Croissants",
      "category": "vegan_options",
      "suppliers": [
        {"supplier_id": 19, "price": 1.80, "quality_score": 8.8},
        {"supplier_id": 21, "price": 2.00, "quality_score": 9.1},
        {"supplier_id": 23, "price": 2.20, "quality_score": 9.0}
      ],
      "unit": "units",
      "reorder_point": 50,
      "optimal_stock": 100,
      "consumption_rate": 30,
      "daily_usage": 30,
      "order_quantity": 80,
      "lead_time": 1,
      "lead_time_unit": "daily",
      "kosher_certified": true,
      "storage_temp": "room_temp",
      "shelf_life_days": 2
    },
    {
      "id": 67,
      "name": "Sourdough Bread Loaves",
      "category": "artisan_breads",
      "suppliers": [
        {"supplier_id": 21, "price": 3.50, "quality_score": 9.5},
        {"supplier_id": 1, "price": 3.20, "quality_score": 8.9},
        {"supplier_id": 19, "price": 3.30, "quality_score": 9.0}
      ],
      "unit": "units",
      "reorder_point": 30,
      "optimal_stock": 60,
      "consumption_rate": 25,
      "daily_usage": 25,
      "order_quantity": 50,
      "lead_time": 1,
      "lead_time_unit": "daily",
      "kosher_certified": true,
      "storage_temp": "room_temp",
      "shelf_life_days": 3
    },
    {
      "id": 68,
      "name": "Gourmet Doughnuts Assorted",
      "category": "desserts",
      "suppliers": [
        {"supplier_id": 22, "price": 2.00, "quality_score": 9.3},
        {"supplier_id": 20, "price": 1.80, "quality_score": 8.8},
        {"supplier_id": 19, "price": 1.90, "quality_score": 8.9}
      ],
      "unit": "units",
      "reorder_point": 36,
      "optimal_stock": 72,
      "consumption_rate": 24,
      "daily_usage": 24,
      "order_quantity": 48,
      "lead_time": 1,
      "lead_time_unit": "daily",
      "kosher_certified": false,
      "storage_temp": "room_temp",
      "shelf_life_days": 1
    },
    {
      "id": 69,
      "name": "Organic Granola",
      "category": "breakfast_items",
      "suppliers": [
        {"supplier_id": 23, "price": 12.00, "quality_score": 9.0},
        {"supplier_id": 24, "price": 11.50, "quality_score": 8.8},
        {"supplier_id": 3, "price": 13.00, "quality_score": 8.5}
      ],
      "unit": "kg",
      "reorder_point": 10,
      "optimal_stock": 20,
      "consumption_rate": 3,
      "daily_usage": 3,
      "order_quantity": 15,
      "lead_time": 2,
      "lead_time_unit": "daily",
      "kosher_certified": true,
      "storage_temp": "room_temp",
      "shelf_life_days": 90
    },
    {
      "id": 70,
      "name": "Overnight Oats Mix",
      "category": "breakfast_items",
      "suppliers": [
        {"supplier_id": 23, "price": 8.00, "quality_score": 8.9},
        {"supplier_id": 24, "price": 7.50, "quality_score": 8.7},
        {"supplier_id": 3, "price": 8.50, "quality_score": 8.6}
      ],
      "unit": "kg",
      "reorder_point": 8,
      "optimal_stock": 15,
      "consumption_rate": 2,
      "daily_usage": 2,
      "order_quantity": 10,
      "lead_time": 2,
      "lead_time_unit": "daily",
      "kosher_certified": true,
      "storage_temp": "room_temp",
      "shelf_life_days": 120
    },
    {
      "id": 71,
      "name": "Avocado (Ripe)",
      "category": "fresh_produce",
      "suppliers": [
        {"supplier_id": 24, "price": 1.20, "quality_score": 9.0},
        {"supplier_id": 25, "price": 1.00, "quality_score": 8.8},
        {"supplier_id": 8, "price": 1.30, "quality_score": 8.7}
      ],
      "unit": "units",
      "reorder_point": 50,
      "optimal_stock": 100,
      "consumption_rate": 40,
      "daily_usage": 40,
      "order_quantity": 80,
      "lead_time": 1,
      "lead_time_unit": "daily",
      "kosher_certified": true,
      "storage_temp": "cool",
      "shelf_life_days": 3
    },
    {
      "id": 72,
      "name": "Mixed Baby Leaves Salad",
      "category": "salad_components",
      "suppliers": [
        {"supplier_id": 25, "price": 6.00, "quality_score": 9.1},
        {"supplier_id": 24, "price": 6.50, "quality_score": 9.0},
        {"supplier_id": 8, "price": 7.00, "quality_score": 8.8}
      ],
      "unit": "kg",
      "reorder_point": 15,
      "optimal_stock": 30,
      "consumption_rate": 10,
      "daily_usage": 10,
      "order_quantity": 25,
      "lead_time": 1,
      "lead_time_unit": "daily",
      "kosher_certified": true,
      "storage_temp": "refrigerated",
      "shelf_life_days": 5
    },
    {
      "id": 73,
      "name": "Vegan Mayo",
      "category": "condiments_sauces",
      "suppliers": [
        {"supplier_id": 12, "price": 4.50, "quality_score": 8.7},
        {"supplier_id": 23, "price": 5.00, "quality_score": 9.0},
        {"supplier_id": 24, "price": 4.80, "quality_score": 8.8}
      ],
      "unit": "litre",
      "reorder_point": 10,
      "optimal_stock": 20,
      "consumption_rate": 3,
      "daily_usage": 3,
      "order_quantity": 15,
      "lead_time": 2,
      "lead_time_unit": "daily",
      "kosher_certified": true,
      "storage_temp": "refrigerated",
      "shelf_life_days": 180
    },
    {
      "id": 74,
      "name": "Biodegradable Coffee Cups (12oz)",
      "category": "eco_packaging",
      "suppliers": [
        {"supplier_id": 11, "price": 0.15, "quality_score": 9.0},
        {"supplier_id": 24, "price": 0.18, "quality_score": 9.2},
        {"supplier_id": 3, "price": 0.16, "quality_score": 8.8}
      ],
      "unit": "units",
      "reorder_point": 1000,
      "optimal_stock": 2500,
      "consumption_rate": 500,
      "daily_usage": 500,
      "order_quantity": 2000,
      "lead_time": 3,
      "lead_time_unit": "daily",
      "kosher_certified": true,
      "storage_temp": "room_temp",
      "shelf_life_days": 730
    },
    {
      "id": 75,
      "name": "Compostable Straws",
      "category": "eco_packaging",
      "suppliers": [
        {"supplier_id": 11, "price": 0.08, "quality_score": 8.9},
        {"supplier_id": 24, "price": 0.10, "quality_score": 9.1},
        {"supplier_id": 3, "price": 0.09, "quality_score": 8.8}
      ],
      "unit": "units",
      "reorder_point": 2000,
      "optimal_stock": 5000,
      "consumption_rate": 800,
      "daily_usage": 800,
      "order_quantity": 4000,
      "lead_time": 3,
      "lead_time_unit": "daily",
      "kosher_certified": true,
      "storage_temp": "room_temp",
      "shelf_life_days": 730
    }
  ]
}